charms/contextual_status.py
charms_contextual_status-0.0.1.dist-info/licenses/LICENSE
tests/unit/test_contextual_status.py
charms_contextual_status-0.0.1.dist-info/METADATA
charms_contextual_status-0.0.1.dist-info/WHEEL
charms_contextual_status-0.0.1.dist-info/top_level.txt
charms_contextual_status-0.0.1.dist-info/zip-safe
charms_contextual_status-0.0.1.dist-info/RECORD
