Metadata-Version: 2.4
Name: charms.contextual-status
Version: 0.0.1
Summary: Charm library for handling unit status with contexts
Author-email: George Kraft <george.kraft@canonical.com>, Adam Dyess <adam.dyess@canonical.com>, Mateo Florido <mateo.florido@canonical.com>
License: Apache
Project-URL: Homepage, https://github.com/charmed-kubernetes/charm-lib-contextual-status
Project-URL: Bug Tracker, https://github.com/charmed-kubernetes/charm-lib-contextual-status/issues
Keywords: juju,charming,ops,framework
Classifier: License :: OSI Approved :: Apache Software License
Classifier: Programming Language :: Python :: 3
Classifier: Programming Language :: Python :: 3.8
Classifier: Programming Language :: Python :: 3.9
Classifier: Programming Language :: Python :: 3.10
Classifier: Programming Language :: Python :: 3.11
Classifier: Programming Language :: Python :: 3.12
Requires-Python: >=3.8
License-File: LICENSE
Requires-Dist: ops
Dynamic: license-file
